wirecard/__init__.py
wirecard/constants.py
wirecard/exceptions.py
wirecard/wirecard.py
wirecard-0.3.0.dist-info/LICENSE
wirecard-0.3.0.dist-info/WHEEL
wirecard-0.3.0.dist-info/METADATA
wirecard-0.3.0.dist-info/RECORD
