Metadata-Version: 2.1
Name: wirecard
Version: 0.3.0
Summary: A Python wrapper for the Wirecard REST API.
Home-page: https://github.com/Flickswitch/wirecard
Author: Jonatas Baldin
Author-email: jonatas.baldin@gmail.com
Requires-Python: >=3.7,<4.0
Classifier: Programming Language :: Python :: 3
Classifier: Programming Language :: Python :: 3.7
Classifier: Programming Language :: Python :: 3.8
Requires-Dist: glom (>=20.8.0,<21.0.0)
Requires-Dist: requests (>=2.24,<3.0)
Project-URL: Repository, https://github.com/Flickswitch/wirecard
